{
  "status": "success",
  "source_sha": "67fd392e1794d781627f38a7319f1dcd0e1b2635",
  "checked_at": "2026-07-19T14:35:28.813880+00:00",
  "architecture": "conversion-voice-v10",
  "home_live": "v4",
  "landing_conversion": "v5",
  "critical_routes": [
    "/",
    "/direct/",
    "/emissions/",
    "/studio/",
    "/api/health",
    "/api/public/catalog",
    "/api/admin/clients",
    "/api/admin/client-update"
  ],
  "outcomes": {
    "normalize": "success",
    "install": "success",
    "validate": "success",
    "deploy": "success",
    "verify": "success"
  }
}
