{
  "status": "failed",
  "source_sha": "0eb032af17bfa9ff40dd63d7c921a7c8db62fc7a",
  "source_workflow_id": "29697675650",
  "ui_workflow_run_id": "29697693292",
  "checked_at": "2026-07-19T17:54:19.248129+00:00",
  "architecture": "conversion-voice-v10",
  "experience": "final-v12",
  "audit": "playwright-production",
  "viewports": [
    "1440x1100",
    "834x1112",
    "390x844"
  ],
  "routes": [
    "/",
    "/emissions/",
    "/direct/"
  ],
  "issues": [
    "home-desktop: navigation de progression absente"
  ],
  "pages": [
    {
      "name": "home-desktop",
      "route": "/",
      "issues": [
        "navigation de progression absente"
      ],
      "width": 1440,
      "height": 1100,
      "scrollHeight": 9272
    },
    {
      "name": "home-tablet",
      "route": "/",
      "issues": [],
      "width": 834,
      "height": 1112,
      "scrollHeight": 9970
    },
    {
      "name": "home-mobile",
      "route": "/",
      "issues": [],
      "width": 390,
      "height": 844,
      "scrollHeight": 11877
    },
    {
      "name": "emissions-desktop",
      "route": "/emissions/",
      "issues": [],
      "width": 1440,
      "height": 1000,
      "scrollHeight": 2036
    },
    {
      "name": "emissions-mobile",
      "route": "/emissions/",
      "issues": [],
      "width": 390,
      "height": 844,
      "scrollHeight": 2788
    },
    {
      "name": "direct-desktop",
      "route": "/direct/",
      "issues": [],
      "width": 1440,
      "height": 1000,
      "scrollHeight": 2006
    }
  ]
}
